deepspace/__init__.py
deepspace/__version__.py
deepspace/sequence/__init__.py
deepspace/tabular/__init__.py
deepspace/tabular/dense_skipco.py
deepspace/tabular/feed_forward.py
deepspace/tabular/one_layer.py
deepspace/tabular/supervised_reg_auto_encoder.py
deepspace-0.0.6.dist-info/LICENSE
deepspace-0.0.6.dist-info/METADATA
deepspace-0.0.6.dist-info/WHEEL
deepspace-0.0.6.dist-info/top_level.txt
deepspace-0.0.6.dist-info/RECORD
